excelify/__init__.py
excelify/excelify.py
excelify/tests.py
excelify-0.4.dist-info/DESCRIPTION.rst
excelify-0.4.dist-info/LICENSE.txt
excelify-0.4.dist-info/METADATA
excelify-0.4.dist-info/RECORD
excelify-0.4.dist-info/WHEEL
excelify-0.4.dist-info/metadata.json
excelify-0.4.dist-info/top_level.txt
