Metadata-Version: 2.0
Name: excelify
Version: 0.4
Summary: IPython magic function to export pandas objects to excel
Home-page: https://github.com/pbaumgartner/excelify
Author: Peter Baumgartner
Author-email: petermbaumgartner@gmail.com
License: MIT
Platform: UNKNOWN
Requires-Dist: ipython
Requires-Dist: pandas
Requires-Dist: XlsxWriter
Requires-Dist: xlrd
